{
	"configurations" : 
	[
		{
			"directories" : 
			[
				{
					"build" : ".",
					"jsonFile" : "directory-.-Debug-f5ebdc15457944623624.json",
					"minimumCMakeVersion" : 
					{
						"string" : "3.28"
					},
					"projectIndex" : 0,
					"source" : ".",
					"targetIndexes" : 
					[
						0,
						1
					]
				}
			],
			"name" : "Debug",
			"projects" : 
			[
				{
					"directoryIndexes" : 
					[
						0
					],
					"name" : "renderTest",
					"targetIndexes" : 
					[
						0,
						1
					]
				}
			],
			"targets" : 
			[
				{
					"directoryIndex" : 0,
					"id" : "imgui::@6890427a1f51a3e7e1df",
					"jsonFile" : "target-imgui-Debug-8fdb3fde3cc9e0f59a08.json",
					"name" : "imgui",
					"projectIndex" : 0
				},
				{
					"directoryIndex" : 0,
					"id" : "renderTest::@6890427a1f51a3e7e1df",
					"jsonFile" : "target-renderTest-Debug-04a501356e4644c0246e.json",
					"name" : "renderTest",
					"projectIndex" : 0
				}
			]
		}
	],
	"kind" : "codemodel",
	"paths" : 
	{
		"build" : "/Users/hayde/Documents/Projects/Personal/renderTest/cmake-build-debug",
		"source" : "/Users/hayde/Documents/Projects/Personal/renderTest"
	},
	"version" : 
	{
		"major" : 2,
		"minor" : 6
	}
}
